django_user_agents/models.py
django_user_agents/__init__.py
django_user_agents/middleware.py
django_user_agents/utils.py
django_user_agents/templatetags/user_agents.py
django_user_agents/templatetags/__init__.py
django_user_agents/tests/views.py
django_user_agents/tests/tests.py
django_user_agents/tests/__init__.py
django_user_agents/tests/urls.py
django_user_agents/tests/settings.py
django_user_agents-0.3.2.dist-info/METADATA
django_user_agents-0.3.2.dist-info/WHEEL
django_user_agents-0.3.2.dist-info/top_level.txt
django_user_agents-0.3.2.dist-info/RECORD
django_user_agents-0.3.2.dist-info/DESCRIPTION.rst
django_user_agents-0.3.2.dist-info/metadata.json
